eapt/__init__.py
eapt/__main__.py
eapt/core.py
eapt/repoutil.py
eapt/resolver.py
eapt-0.1.1.dist-info/LICENSE
eapt-0.1.1.dist-info/METADATA
eapt-0.1.1.dist-info/WHEEL
eapt-0.1.1.dist-info/entry_points.txt
eapt-0.1.1.dist-info/top_level.txt
eapt-0.1.1.dist-info/zip-safe
eapt-0.1.1.dist-info/RECORD
